{
	"class" : {
		 },
	"instance" : {
		"addQuestion" : "ape 5/14/2022 09:38",
		"addQuestionBuilder:" : " 6/27/2022 00:10:02",
		"addQuestionButtonFrame" : " 6/27/2022 00:10:02",
		"buildAddQuestionButtonWith:" : "ms 6/19/2022 21:08",
		"buildManageUserSetsButton:" : "ms 6/19/2022 21:08",
		"buildMaxNumberOfChoicesInputWith:" : "ms 6/19/2022 21:10",
		"buildMaxNumberOfChoicesLabelWith:" : "ms 6/19/2022 21:09",
		"buildQuestionBuilder" : " 6/27/2022 00:10:02",
		"buildQuestionListWith:" : " 6/27/2022 00:10:02",
		"buildRunPollButtonWith:" : "ms 6/19/2022 21:08",
		"buildWith:" : "ms 6/19/2022 20:57",
		"choiceList:" : "kge 6/19/2022 16:43",
		"currentQuestion" : " 6/27/2022 00:10:02",
		"currentQuestion:" : " 6/27/2022 00:10:02",
		"frame:fromTop:fromLeft:width:" : " 6/27/2022 00:10:02",
		"generateRandomID" : "bwe 5/17/2022 21:33",
		"getIndex" : " 6/27/2022 00:10:02",
		"initialize" : " 6/27/2022 00:10:02",
		"list" : " 6/27/2022 00:10:02",
		"openManageUserSetsMenu" : "ms 6/19/2022 21:10",
		"pollDraft" : "CG 7/30/2021 19:06",
		"pollDraft:" : "CG 7/30/2021 19:06",
		"questionBuilderAt:" : " 6/27/2022 00:10:02",
		"questionBuilderFrame" : " 6/27/2022 00:10:02",
		"questionBuilders" : " 6/27/2022 00:10:02",
		"questionBuilders:" : " 6/27/2022 00:10:02",
		"questionListFrame" : " 6/27/2022 00:10:02",
		"runPoll" : "bn 6/13/2022 13:32",
		"runPollButtonFrame" : " 6/27/2022 00:10:02",
		"setIndex:" : " 6/27/2022 00:10:02" } }
