{
	"class" : {
		"isServerActive" : "kge 6/25/2022 16:30",
		"pollRepo" : "ape 6/19/2022 15:11",
		"pollRepo:" : "ape 6/19/2022 13:17",
		"resetPollRepo" : "ms 6/19/2022 19:15",
		"serverActive:" : "kge 6/25/2022 16:34",
		"startServer" : "kge 7/21/2022 15:43",
		"stopServer" : "kge 7/21/2022 14:34" },
	"instance" : {
		"addAnswerSet:FromUser:ToPoll:" : "kge 7/15/2022 11:39",
		"httpGet:" : "kge 7/21/2022 22:04",
		"httpGetGroup:" : "kge 7/15/2022 12:20",
		"httpGetPoll:" : "kge 7/21/2022 15:33",
		"httpPost:" : "kge 7/14/2022 19:36",
		"httpPostAddAnswerSet:" : "kge 7/21/2022 20:44",
		"initialize" : "ms 6/19/2022 19:59",
		"onRequest:" : "ms 6/19/2022 19:59",
		"request:isAuthenticatedFor:" : "bn 7/14/2022 22:35",
		"sanitizePoll:" : "kge 7/21/2022 15:18",
		"send401Response:" : "ms 6/19/2022 20:13" } }
